clipped/__init__.py
clipped/formatting.py
clipped/manager_interface.py
clipped/pkg.py
clipped/_vendor/__init__.py
clipped/_vendor/croniter/__init__.py
clipped/_vendor/croniter/croniter.py
clipped/_vendor/version/__init__.py
clipped/compact/__init__.py
clipped/compact/pydantic.py
clipped/config/__init__.py
clipped/config/constants.py
clipped/config/contexts.py
clipped/config/exceptions.py
clipped/config/manager.py
clipped/config/parser.py
clipped/config/patch_strategy.py
clipped/config/reader.py
clipped/config/schema.py
clipped/config/spec.py
clipped/decorators/__init__.py
clipped/decorators/cached_property.py
clipped/decorators/deprecation.py
clipped/decorators/memoization.py
clipped/decorators/signals.py
clipped/types/__init__.py
clipped/types/base_url.py
clipped/types/docker_image.py
clipped/types/email.py
clipped/types/gcs.py
clipped/types/lists.py
clipped/types/numbers.py
clipped/types/ref_or_obj.py
clipped/types/s3.py
clipped/types/strings.py
clipped/types/uri.py
clipped/types/uuids.py
clipped/types/wasb.py
clipped/utils/__init__.py
clipped/utils/assertions.py
clipped/utils/bools.py
clipped/utils/click.py
clipped/utils/cmd.py
clipped/utils/coroutine.py
clipped/utils/csv.py
clipped/utils/dates.py
clipped/utils/dicts.py
clipped/utils/encoding.py
clipped/utils/enums.py
clipped/utils/env.py
clipped/utils/git.py
clipped/utils/hashing.py
clipped/utils/http.py
clipped/utils/humanize.py
clipped/utils/imports.py
clipped/utils/indentation.py
clipped/utils/json.py
clipped/utils/lists.py
clipped/utils/logging.py
clipped/utils/np.py
clipped/utils/paths.py
clipped/utils/processes.py
clipped/utils/query_params.py
clipped/utils/requests.py
clipped/utils/responses.py
clipped/utils/sanitizers.py
clipped/utils/serialization.py
clipped/utils/strings.py
clipped/utils/tz.py
clipped/utils/units.py
clipped/utils/urls.py
clipped/utils/validation.py
clipped/utils/versions.py
clipped/utils/workers.py
clipped/utils/yaml.py
clipped-0.11.3.dist-info/LICENSE
clipped-0.11.3.dist-info/METADATA
clipped-0.11.3.dist-info/WHEEL
clipped-0.11.3.dist-info/top_level.txt
clipped-0.11.3.dist-info/RECORD
